libname/__init__.py
libname/hello.py
vidstreammmjka/__init__.py
vidstreammmjka/hello.py
vidstreammmjka/helloworld.kv
vidstreammmjka-1.3.dist-info/METADATA
vidstreammmjka-1.3.dist-info/WHEEL
vidstreammmjka-1.3.dist-info/top_level.txt
vidstreammmjka-1.3.dist-info/RECORD
